{"Type": "OrderPlaced", "Data": {"TimeStampUtc": "2018-10-03T23:39:18Z", "OrderId": "463e80ef-7009-4ed7-aa24-c129d67c8be7"}}
{"Type": "OrderAccepted", "Data": {"TimeStampUtc": "2018-10-03T23:39:18Z", "OrderId": "463e80ef-7009-4ed7-aa24-c129d67c8be7"}}
{"Type": "OrderPlaced", "Data": {"TimeStampUtc": "2018-10-03T23:39:18Z", "OrderId": "c6930921-f389-41b4-ad2d-9c88f99c05ad"}}
{"Type": "OrderCancelled", "Data": {"TimeStampUtc": "2018-10-03T23:39:18Z", "OrderId": "c6930921-f389-41b4-ad2d-9c88f99c05ad"}}
{"Type": "OrderPlaced", "Data": {"TimeStampUtc": "2018-10-03T23:39:18Z", "OrderId": "41e034a0-dc8c-449a-9778-570544a8ec8f"}}
{"Type": "OrderAccepted", "Data": {"TimeStampUtc": "2018-10-03T23:39:18Z", "OrderId": "41e034a0-dc8c-449a-9778-570544a8ec8f"}}
{"Type": "OrderPlaced", "Data": {"TimeStampUtc": "2018-10-03T23:39:18Z", "OrderId": "f73c4027-d562-45c3-a8d2-2fdb577e5879"}}
{"Type": "OrderAccepted", "Data": {"TimeStampUtc": "2018-10-03T23:39:18Z", "OrderId": "f73c4027-d562-45c3-a8d2-2fdb577e5879"}}
{"Type": "OrderPlaced", "Data": {"TimeStampUtc": "2018-10-03T23:39:18Z", "OrderId": "d181116b-33cd-4713-b588-dee4e8a586d9"}}
{"Type": "OrderAccepted", "Data": {"TimeStampUtc": "2018-10-03T23:39:18Z", "OrderId": "d181116b-33cd-4713-b588-dee4e8a586d9"}}
{"Type": "OrderPlaced", "Data": {"TimeStampUtc": "2018-10-03T23:39:18Z", "OrderId": "9e81329d-c8d4-4e74-aed9-0cc329885ecd"}}
{"Type": "OrderAccepted", "Data": {"TimeStampUtc": "2018-10-03T23:39:18Z", "OrderId": "9e81329d-c8d4-4e74-aed9-0cc329885ecd"}}
{"Type": "OrderPlaced", "Data": {"TimeStampUtc": "2018-10-03T23:39:18Z", "OrderId": "f7a45510-0fa7-496b-83d4-5a791dc36c69"}}
{"Type": "OrderCancelled", "Data": {"TimeStampUtc": "2018-10-03T23:39:18Z", "OrderId": "f7a45510-0fa7-496b-83d4-5a791dc36c69"}}
{"Type": "OrderPlaced", "Data": {"TimeStampUtc": "2018-10-03T23:39:18Z", "OrderId": "9a1752f6-a8eb-4ed9-9b3c-b9195ccd5d5a"}}
{"Type": "OrderAccepted", "Data": {"TimeStampUtc": "2018-10-03T23:39:18Z", "OrderId": "9a1752f6-a8eb-4ed9-9b3c-b9195ccd5d5a"}}
{"Type": "OrderPlaced", "Data": {"TimeStampUtc": "2018-10-03T23:39:18Z", "OrderId": "5a973f82-dfb8-4c0d-9391-48ee70d99aa3"}}
{"Type": "OrderAccepted", "Data": {"TimeStampUtc": "2018-10-03T23:39:18Z", "OrderId": "5a973f82-dfb8-4c0d-9391-48ee70d99aa3"}}
{"Type": "OrderPlaced", "Data": {"TimeStampUtc": "2018-10-03T23:39:18Z", "OrderId": "ed725513-f28c-474f-b235-147180aceca6"}}
{"Type": "OrderAccepted", "Data": {"TimeStampUtc": "2018-10-03T23:39:18Z", "OrderId": "ed725513-f28c-474f-b235-147180aceca6"}}
{"Type": "OrderPlaced", "Data": {"TimeStampUtc": "2018-10-03T23:39:18Z", "OrderId": "e7f97f0f-1419-454c-bc19-ec089a26a678"}}
{"Type": "OrderAccepted", "Data": {"TimeStampUtc": "2018-10-03T23:39:18Z", "OrderId": "e7f97f0f-1419-454c-bc19-ec089a26a678"}}
{"Type": "OrderPlaced", "Data": {"TimeStampUtc": "2018-10-03T23:39:18Z", "OrderId": "b502122b-f080-4445-89a9-fe794430e12f"}}
{"Type": "OrderCancelled", "Data": {"TimeStampUtc": "2018-10-03T23:39:18Z", "OrderId": "b502122b-f080-4445-89a9-fe794430e12f"}}
{"Type": "OrderPlaced", "Data": {"TimeStampUtc": "2018-10-03T23:39:18Z", "OrderId": "1cc31f8f-3dda-4a8e-b36d-65dc2e9f27e1"}}
{"Type": "OrderCancelled", "Data": {"TimeStampUtc": "2018-10-03T23:39:18Z", "OrderId": "1cc31f8f-3dda-4a8e-b36d-65dc2e9f27e1"}}
{"Type": "OrderPlaced", "Data": {"TimeStampUtc": "2018-10-03T23:39:18Z", "OrderId": "094cf14d-c163-4029-a7ce-c6ec72647a2b"}}
{"Type": "OrderCancelled", "Data": {"TimeStampUtc": "2018-10-03T23:39:18Z", "OrderId": "094cf14d-c163-4029-a7ce-c6ec72647a2b"}}
{"Type": "OrderPlaced", "Data": {"TimeStampUtc": "2018-10-03T23:39:18Z", "OrderId": "600431c3-0d68-4ce8-a7bb-72c73a568243"}}
{"Type": "OrderAccepted", "Data": {"TimeStampUtc": "2018-10-03T23:39:18Z", "OrderId": "600431c3-0d68-4ce8-a7bb-72c73a568243"}}
{"Type": "OrderPlaced", "Data": {"TimeStampUtc": "2018-10-03T23:39:18Z", "OrderId": "7b962d3e-bfdf-401b-a9a2-0f2e03de6cf1"}}
{"Type": "OrderAccepted", "Data": {"TimeStampUtc": "2018-10-03T23:39:18Z", "OrderId": "7b962d3e-bfdf-401b-a9a2-0f2e03de6cf1"}}
{"Type": "OrderPlaced", "Data": {"TimeStampUtc": "2018-10-03T23:39:18Z", "OrderId": "d3538ca1-60e7-4eee-9bf5-c2377cc9d09d"}}
{"Type": "OrderAccepted", "Data": {"TimeStampUtc": "2018-10-03T23:39:18Z", "OrderId": "d3538ca1-60e7-4eee-9bf5-c2377cc9d09d"}}
{"Type": "OrderPlaced", "Data": {"TimeStampUtc": "2018-10-03T23:39:18Z", "OrderId": "9aca5332-bdd5-4649-8ad8-2ceb3d8194af"}}
{"Type": "OrderCancelled", "Data": {"TimeStampUtc": "2018-10-03T23:39:18Z", "OrderId": "9aca5332-bdd5-4649-8ad8-2ceb3d8194af"}}
{"Type": "OrderPlaced", "Data": {"TimeStampUtc": "2018-10-03T23:39:18Z", "OrderId": "670d1aba-e276-444c-a7ee-899ab148b14a"}}
{"Type": "OrderAccepted", "Data": {"TimeStampUtc": "2018-10-03T23:39:18Z", "OrderId": "670d1aba-e276-444c-a7ee-899ab148b14a"}}
{"Type": "OrderPlaced", "Data": {"TimeStampUtc": "2018-10-03T23:39:18Z", "OrderId": "652abac3-f80e-45bc-9811-22ed3bb4d43d"}}
{"Type": "OrderAccepted", "Data": {"TimeStampUtc": "2018-10-03T23:39:18Z", "OrderId": "652abac3-f80e-45bc-9811-22ed3bb4d43d"}}
{"Type": "OrderPlaced", "Data": {"TimeStampUtc": "2018-10-03T23:39:18Z", "OrderId": "43a08219-277d-4f35-9be4-95ea92ecc1bf"}}
{"Type": "OrderAccepted", "Data": {"TimeStampUtc": "2018-10-03T23:39:18Z", "OrderId": "43a08219-277d-4f35-9be4-95ea92ecc1bf"}}
{"Type": "OrderPlaced", "Data": {"TimeStampUtc": "2018-10-03T23:39:18Z", "OrderId": "4f991701-7041-48ab-9053-fc7a50a8e2cd"}}
{"Type": "OrderAccepted", "Data": {"TimeStampUtc": "2018-10-03T23:39:18Z", "OrderId": "4f991701-7041-48ab-9053-fc7a50a8e2cd"}}
{"Type": "OrderPlaced", "Data": {"TimeStampUtc": "2018-10-03T23:39:18Z", "OrderId": "fbc9fd27-c1a9-4aad-a003-58cb87694bdb"}}
{"Type": "OrderAccepted", "Data": {"TimeStampUtc": "2018-10-03T23:39:18Z", "OrderId": "fbc9fd27-c1a9-4aad-a003-58cb87694bdb"}}
{"Type": "OrderPlaced", "Data": {"TimeStampUtc": "2018-10-03T23:39:18Z", "OrderId": "465e0aee-f634-44e8-9a0f-2ac213a062a4"}}
{"Type": "OrderAccepted", "Data": {"TimeStampUtc": "2018-10-03T23:39:18Z", "OrderId": "465e0aee-f634-44e8-9a0f-2ac213a062a4"}}
{"Type": "OrderPlaced", "Data": {"TimeStampUtc": "2018-10-03T23:39:18Z", "OrderId": "235fa7a5-a126-47f6-bef9-6ec5a6d02e06"}}
{"Type": "OrderCancelled", "Data": {"TimeStampUtc": "2018-10-03T23:39:18Z", "OrderId": "235fa7a5-a126-47f6-bef9-6ec5a6d02e06"}}
{"Type": "OrderPlaced", "Data": {"TimeStampUtc": "2018-10-03T23:39:18Z", "OrderId": "f22100d2-58f9-4289-badd-8c10b5fe4a27"}}
{"Type": "OrderAccepted", "Data": {"TimeStampUtc": "2018-10-03T23:39:18Z", "OrderId": "f22100d2-58f9-4289-badd-8c10b5fe4a27"}}
{"Type": "OrderPlaced", "Data": {"TimeStampUtc": "2018-10-03T23:39:18Z", "OrderId": "14485ac7-ab84-4fdc-bb53-9982d7f812b5"}}
{"Type": "OrderCancelled", "Data": {"TimeStampUtc": "2018-10-03T23:39:18Z", "OrderId": "14485ac7-ab84-4fdc-bb53-9982d7f812b5"}}
{"Type": "OrderPlaced", "Data": {"TimeStampUtc": "2018-10-03T23:39:18Z", "OrderId": "d6e524d2-e1e9-4ef6-b427-48ad84251f06"}}
{"Type": "OrderAccepted", "Data": {"TimeStampUtc": "2018-10-03T23:39:18Z", "OrderId": "d6e524d2-e1e9-4ef6-b427-48ad84251f06"}}
{"Type": "OrderPlaced", "Data": {"TimeStampUtc": "2018-10-03T23:39:18Z", "OrderId": "0b848a44-286f-4ed0-aa66-daffdac0fd7e"}}
{"Type": "OrderCancelled", "Data": {"TimeStampUtc": "2018-10-03T23:39:18Z", "OrderId": "0b848a44-286f-4ed0-aa66-daffdac0fd7e"}}
{"Type": "OrderPlaced", "Data": {"TimeStampUtc": "2018-10-03T23:39:18Z", "OrderId": "b048d34c-58bf-4d6f-b9c7-344bc06eabd5"}}
{"Type": "OrderCancelled", "Data": {"TimeStampUtc": "2018-10-03T23:39:18Z", "OrderId": "b048d34c-58bf-4d6f-b9c7-344bc06eabd5"}}
{"Type": "OrderPlaced", "Data": {"TimeStampUtc": "2018-10-03T23:39:18Z", "OrderId": "f7c16b0f-580d-4c40-9551-36ab488e5496"}}
{"Type": "OrderCancelled", "Data": {"TimeStampUtc": "2018-10-03T23:39:18Z", "OrderId": "f7c16b0f-580d-4c40-9551-36ab488e5496"}}
{"Type": "OrderPlaced", "Data": {"TimeStampUtc": "2018-10-03T23:39:18Z", "OrderId": "43457526-af7b-48ac-801a-1809254d1c35"}}
{"Type": "OrderAccepted", "Data": {"TimeStampUtc": "2018-10-03T23:39:18Z", "OrderId": "43457526-af7b-48ac-801a-1809254d1c35"}}
{"Type": "OrderPlaced", "Data": {"TimeStampUtc": "2018-10-03T23:39:18Z", "OrderId": "02b72b7c-fc02-4137-93f7-1b2eb0fcd13f"}}
{"Type": "OrderCancelled", "Data": {"TimeStampUtc": "2018-10-03T23:39:18Z", "OrderId": "02b72b7c-fc02-4137-93f7-1b2eb0fcd13f"}}
{"Type": "OrderPlaced", "Data": {"TimeStampUtc": "2018-10-03T23:39:18Z", "OrderId": "192dc500-93ab-4dcb-b15f-b1ddb1bc1f3a"}}
{"Type": "OrderAccepted", "Data": {"TimeStampUtc": "2018-10-03T23:39:18Z", "OrderId": "192dc500-93ab-4dcb-b15f-b1ddb1bc1f3a"}}
{"Type": "OrderPlaced", "Data": {"TimeStampUtc": "2018-10-03T23:39:18Z", "OrderId": "bc658fd8-bf0c-4c1c-8430-183adeec64fe"}}
{"Type": "OrderCancelled", "Data": {"TimeStampUtc": "2018-10-03T23:39:18Z", "OrderId": "bc658fd8-bf0c-4c1c-8430-183adeec64fe"}}
{"Type": "OrderPlaced", "Data": {"TimeStampUtc": "2018-10-03T23:39:18Z", "OrderId": "d930bf59-df5f-4f0a-a661-0d9b0bd924f5"}}
{"Type": "OrderAccepted", "Data": {"TimeStampUtc": "2018-10-03T23:39:18Z", "OrderId": "d930bf59-df5f-4f0a-a661-0d9b0bd924f5"}}
{"Type": "OrderPlaced", "Data": {"TimeStampUtc": "2018-10-03T23:39:18Z", "OrderId": "accb678d-f1c1-4e16-92f1-fab50c22a08b"}}
{"Type": "OrderAccepted", "Data": {"TimeStampUtc": "2018-10-03T23:39:18Z", "OrderId": "accb678d-f1c1-4e16-92f1-fab50c22a08b"}}
{"Type": "OrderPlaced", "Data": {"TimeStampUtc": "2018-10-03T23:39:18Z", "OrderId": "65a2902e-eead-4468-aa12-288b0f9146b4"}}
{"Type": "OrderAccepted", "Data": {"TimeStampUtc": "2018-10-03T23:39:18Z", "OrderId": "65a2902e-eead-4468-aa12-288b0f9146b4"}}
{"Type": "OrderPlaced", "Data": {"TimeStampUtc": "2018-10-03T23:39:18Z", "OrderId": "5e1f18fa-5612-41ff-b7f8-31cf637102a4"}}
{"Type": "OrderAccepted", "Data": {"TimeStampUtc": "2018-10-03T23:39:18Z", "OrderId": "5e1f18fa-5612-41ff-b7f8-31cf637102a4"}}
{"Type": "OrderPlaced", "Data": {"TimeStampUtc": "2018-10-03T23:39:18Z", "OrderId": "e89445fe-3f4e-45c8-80d4-e61ca8c8be4f"}}
{"Type": "OrderAccepted", "Data": {"TimeStampUtc": "2018-10-03T23:39:18Z", "OrderId": "e89445fe-3f4e-45c8-80d4-e61ca8c8be4f"}}
{"Type": "OrderPlaced", "Data": {"TimeStampUtc": "2018-10-03T23:39:18Z", "OrderId": "7dc1f73f-32c2-4ac2-8d51-a0106db4f64b"}}
{"Type": "OrderAccepted", "Data": {"TimeStampUtc": "2018-10-03T23:39:18Z", "OrderId": "7dc1f73f-32c2-4ac2-8d51-a0106db4f64b"}}
{"Type": "OrderPlaced", "Data": {"TimeStampUtc": "2018-10-03T23:39:18Z", "OrderId": "b8ded704-e9fb-4196-96dd-dc7669f1406f"}}
{"Type": "OrderAccepted", "Data": {"TimeStampUtc": "2018-10-03T23:39:18Z", "OrderId": "b8ded704-e9fb-4196-96dd-dc7669f1406f"}}
{"Type": "OrderPlaced", "Data": {"TimeStampUtc": "2018-10-03T23:39:18Z", "OrderId": "48229280-ec87-4dcd-a89a-b477949f790f"}}
{"Type": "OrderAccepted", "Data": {"TimeStampUtc": "2018-10-03T23:39:18Z", "OrderId": "48229280-ec87-4dcd-a89a-b477949f790f"}}
{"Type": "OrderPlaced", "Data": {"TimeStampUtc": "2018-10-03T23:39:18Z", "OrderId": "485933e0-3cd0-49e4-9150-4ef1e0b96882"}}
{"Type": "OrderAccepted", "Data": {"TimeStampUtc": "2018-10-03T23:39:18Z", "OrderId": "485933e0-3cd0-49e4-9150-4ef1e0b96882"}}
{"Type": "OrderPlaced", "Data": {"TimeStampUtc": "2018-10-03T23:39:18Z", "OrderId": "ea1fe58f-5399-4cd8-b212-27c0dd0a323d"}}
{"Type": "OrderAccepted", "Data": {"TimeStampUtc": "2018-10-03T23:39:18Z", "OrderId": "ea1fe58f-5399-4cd8-b212-27c0dd0a323d"}}
{"Type": "OrderPlaced", "Data": {"TimeStampUtc": "2018-10-03T23:39:18Z", "OrderId": "08c3ebf1-8e40-4098-9ac7-bb296dfb9eea"}}
{"Type": "OrderAccepted", "Data": {"TimeStampUtc": "2018-10-03T23:39:18Z", "OrderId": "08c3ebf1-8e40-4098-9ac7-bb296dfb9eea"}}
{"Type": "OrderPlaced", "Data": {"TimeStampUtc": "2018-10-03T23:39:18Z", "OrderId": "3db20318-95a1-41c1-b5d7-7dcc5de29357"}}
{"Type": "OrderAccepted", "Data": {"TimeStampUtc": "2018-10-03T23:39:18Z", "OrderId": "3db20318-95a1-41c1-b5d7-7dcc5de29357"}}
{"Type": "OrderPlaced", "Data": {"TimeStampUtc": "2018-10-03T23:39:18Z", "OrderId": "f0c77ccc-3fe5-497a-b7f9-c2126f02584d"}}
{"Type": "OrderAccepted", "Data": {"TimeStampUtc": "2018-10-03T23:39:18Z", "OrderId": "f0c77ccc-3fe5-497a-b7f9-c2126f02584d"}}
{"Type": "OrderPlaced", "Data": {"TimeStampUtc": "2018-10-03T23:39:18Z", "OrderId": "2627d630-1d7c-4f3f-b1be-3917304d6cda"}}
{"Type": "OrderAccepted", "Data": {"TimeStampUtc": "2018-10-03T23:39:18Z", "OrderId": "2627d630-1d7c-4f3f-b1be-3917304d6cda"}}
{"Type": "OrderPlaced", "Data": {"TimeStampUtc": "2018-10-03T23:39:18Z", "OrderId": "f0120621-a059-4c0d-95ac-ccf0a6ca9740"}}
{"Type": "OrderAccepted", "Data": {"TimeStampUtc": "2018-10-03T23:39:18Z", "OrderId": "f0120621-a059-4c0d-95ac-ccf0a6ca9740"}}
{"Type": "OrderPlaced", "Data": {"TimeStampUtc": "2018-10-03T23:39:18Z", "OrderId": "2a18f1e5-0eee-45b1-82af-47984d71d221"}}
{"Type": "OrderAccepted", "Data": {"TimeStampUtc": "2018-10-03T23:39:18Z", "OrderId": "2a18f1e5-0eee-45b1-82af-47984d71d221"}}
{"Type": "OrderPlaced", "Data": {"TimeStampUtc": "2018-10-03T23:39:18Z", "OrderId": "ec3365cd-8584-4c9b-8b67-6c793d484d26"}}
{"Type": "OrderCancelled", "Data": {"TimeStampUtc": "2018-10-03T23:39:18Z", "OrderId": "ec3365cd-8584-4c9b-8b67-6c793d484d26"}}
{"Type": "OrderPlaced", "Data": {"TimeStampUtc": "2018-10-03T23:39:18Z", "OrderId": "217a4c89-36e4-40b5-bb04-bf41681b9297"}}
{"Type": "OrderAccepted", "Data": {"TimeStampUtc": "2018-10-03T23:39:18Z", "OrderId": "217a4c89-36e4-40b5-bb04-bf41681b9297"}}
{"Type": "OrderPlaced", "Data": {"TimeStampUtc": "2018-10-03T23:39:18Z", "OrderId": "a80f5214-588d-4e10-87e2-172ad4af4433"}}
{"Type": "OrderCancelled", "Data": {"TimeStampUtc": "2018-10-03T23:39:18Z", "OrderId": "a80f5214-588d-4e10-87e2-172ad4af4433"}}
{"Type": "OrderPlaced", "Data": {"TimeStampUtc": "2018-10-03T23:39:18Z", "OrderId": "2749129a-b680-4e8e-bfee-0700820f63aa"}}
{"Type": "OrderAccepted", "Data": {"TimeStampUtc": "2018-10-03T23:39:18Z", "OrderId": "2749129a-b680-4e8e-bfee-0700820f63aa"}}
{"Type": "OrderPlaced", "Data": {"TimeStampUtc": "2018-10-03T23:39:18Z", "OrderId": "aa273aeb-a003-440c-b9b1-e8fc6626ea06"}}
{"Type": "OrderAccepted", "Data": {"TimeStampUtc": "2018-10-03T23:39:18Z", "OrderId": "aa273aeb-a003-440c-b9b1-e8fc6626ea06"}}
{"Type": "OrderPlaced", "Data": {"TimeStampUtc": "2018-10-03T23:39:18Z", "OrderId": "726e8e75-a482-47e9-8edb-e303c5b70f02"}}
{"Type": "OrderAccepted", "Data": {"TimeStampUtc": "2018-10-03T23:39:18Z", "OrderId": "726e8e75-a482-47e9-8edb-e303c5b70f02"}}
{"Type": "OrderPlaced", "Data": {"TimeStampUtc": "2018-10-03T23:39:18Z", "OrderId": "12891257-15ec-4b5e-b441-584d422ee1c6"}}
{"Type": "OrderAccepted", "Data": {"TimeStampUtc": "2018-10-03T23:39:18Z", "OrderId": "12891257-15ec-4b5e-b441-584d422ee1c6"}}
{"Type": "OrderPlaced", "Data": {"TimeStampUtc": "2018-10-03T23:39:18Z", "OrderId": "6e816bac-87fb-4904-8347-60d6792b9246"}}
{"Type": "OrderAccepted", "Data": {"TimeStampUtc": "2018-10-03T23:39:18Z", "OrderId": "6e816bac-87fb-4904-8347-60d6792b9246"}}
{"Type": "OrderPlaced", "Data": {"TimeStampUtc": "2018-10-03T23:39:18Z", "OrderId": "9e15be00-a518-4237-868e-ec2b0bba2026"}}
{"Type": "OrderAccepted", "Data": {"TimeStampUtc": "2018-10-03T23:39:18Z", "OrderId": "9e15be00-a518-4237-868e-ec2b0bba2026"}}
{"Type": "OrderPlaced", "Data": {"TimeStampUtc": "2018-10-03T23:39:18Z", "OrderId": "9b24a128-036b-46ee-82eb-d388b2253cfe"}}
{"Type": "OrderAccepted", "Data": {"TimeStampUtc": "2018-10-03T23:39:18Z", "OrderId": "9b24a128-036b-46ee-82eb-d388b2253cfe"}}
{"Type": "OrderPlaced", "Data": {"TimeStampUtc": "2018-10-03T23:39:18Z", "OrderId": "5fedb7de-2603-46e5-a6a0-6f68c4ec7476"}}
{"Type": "OrderCancelled", "Data": {"TimeStampUtc": "2018-10-03T23:39:18Z", "OrderId": "5fedb7de-2603-46e5-a6a0-6f68c4ec7476"}}
{"Type": "OrderPlaced", "Data": {"TimeStampUtc": "2018-10-03T23:39:18Z", "OrderId": "3ef55bbc-5da9-44b9-8175-37056cf76546"}}
{"Type": "OrderAccepted", "Data": {"TimeStampUtc": "2018-10-03T23:39:18Z", "OrderId": "3ef55bbc-5da9-44b9-8175-37056cf76546"}}
{"Type": "OrderPlaced", "Data": {"TimeStampUtc": "2018-10-03T23:39:18Z", "OrderId": "1f63cb4d-e7a5-4c0c-b6e4-357ee3c3e580"}}
{"Type": "OrderAccepted", "Data": {"TimeStampUtc": "2018-10-03T23:39:18Z", "OrderId": "1f63cb4d-e7a5-4c0c-b6e4-357ee3c3e580"}}
{"Type": "OrderPlaced", "Data": {"TimeStampUtc": "2018-10-03T23:39:18Z", "OrderId": "ff6c5c3a-9561-4dc8-a805-9b196b9924c3"}}
{"Type": "OrderAccepted", "Data": {"TimeStampUtc": "2018-10-03T23:39:18Z", "OrderId": "ff6c5c3a-9561-4dc8-a805-9b196b9924c3"}}
{"Type": "OrderPlaced", "Data": {"TimeStampUtc": "2018-10-03T23:39:18Z", "OrderId": "c66a6299-b93b-4680-848d-c28eb9ad59f8"}}
{"Type": "OrderAccepted", "Data": {"TimeStampUtc": "2018-10-03T23:39:18Z", "OrderId": "c66a6299-b93b-4680-848d-c28eb9ad59f8"}}
{"Type": "OrderPlaced", "Data": {"TimeStampUtc": "2018-10-03T23:39:18Z", "OrderId": "5ecf1ff3-1bb1-429e-b073-67cae0a802bc"}}
{"Type": "OrderAccepted", "Data": {"TimeStampUtc": "2018-10-03T23:39:18Z", "OrderId": "5ecf1ff3-1bb1-429e-b073-67cae0a802bc"}}
{"Type": "OrderPlaced", "Data": {"TimeStampUtc": "2018-10-03T23:39:18Z", "OrderId": "3d6c9b90-336d-445a-a87e-2b3e72d42f0a"}}
{"Type": "OrderAccepted", "Data": {"TimeStampUtc": "2018-10-03T23:39:18Z", "OrderId": "3d6c9b90-336d-445a-a87e-2b3e72d42f0a"}}
{"Type": "OrderPlaced", "Data": {"TimeStampUtc": "2018-10-03T23:39:18Z", "OrderId": "f16c6b92-f40a-493d-bb35-4524f737892f"}}
{"Type": "OrderAccepted", "Data": {"TimeStampUtc": "2018-10-03T23:39:18Z", "OrderId": "f16c6b92-f40a-493d-bb35-4524f737892f"}}
{"Type": "OrderPlaced", "Data": {"TimeStampUtc": "2018-10-03T23:39:18Z", "OrderId": "607037c2-f246-4f84-88d7-364cbd0608b2"}}
{"Type": "OrderAccepted", "Data": {"TimeStampUtc": "2018-10-03T23:39:18Z", "OrderId": "607037c2-f246-4f84-88d7-364cbd0608b2"}}
{"Type": "OrderPlaced", "Data": {"TimeStampUtc": "2018-10-03T23:39:18Z", "OrderId": "160a6296-d067-43cd-b4c9-521b0aa6602e"}}
{"Type": "OrderAccepted", "Data": {"TimeStampUtc": "2018-10-03T23:39:18Z", "OrderId": "160a6296-d067-43cd-b4c9-521b0aa6602e"}}
{"Type": "OrderPlaced", "Data": {"TimeStampUtc": "2018-10-03T23:39:18Z", "OrderId": "5875892a-9bb9-4bb3-b354-e0c0a73894ae"}}
{"Type": "OrderCancelled", "Data": {"TimeStampUtc": "2018-10-03T23:39:18Z", "OrderId": "5875892a-9bb9-4bb3-b354-e0c0a73894ae"}}
{"Type": "OrderPlaced", "Data": {"TimeStampUtc": "2018-10-03T23:39:18Z", "OrderId": "8c76d7dd-c0b0-44dc-bb76-4f9469a29cb3"}}
{"Type": "OrderAccepted", "Data": {"TimeStampUtc": "2018-10-03T23:39:18Z", "OrderId": "8c76d7dd-c0b0-44dc-bb76-4f9469a29cb3"}}
{"Type": "OrderPlaced", "Data": {"TimeStampUtc": "2018-10-03T23:39:18Z", "OrderId": "e41f7dd2-e79d-404d-b01f-3d7503f85776"}}
{"Type": "OrderAccepted", "Data": {"TimeStampUtc": "2018-10-03T23:39:18Z", "OrderId": "e41f7dd2-e79d-404d-b01f-3d7503f85776"}}
{"Type": "OrderPlaced", "Data": {"TimeStampUtc": "2018-10-03T23:39:18Z", "OrderId": "50e39d3c-bb92-4e3d-90fb-c5169be77e28"}}
{"Type": "OrderCancelled", "Data": {"TimeStampUtc": "2018-10-03T23:39:18Z", "OrderId": "50e39d3c-bb92-4e3d-90fb-c5169be77e28"}}
{"Type": "OrderPlaced", "Data": {"TimeStampUtc": "2018-10-03T23:39:18Z", "OrderId": "9726db71-63f4-41d5-95cc-5f5f721d4b34"}}
{"Type": "OrderAccepted", "Data": {"TimeStampUtc": "2018-10-03T23:39:18Z", "OrderId": "9726db71-63f4-41d5-95cc-5f5f721d4b34"}}
{"Type": "OrderPlaced", "Data": {"TimeStampUtc": "2018-10-03T23:39:18Z", "OrderId": "7d3a4526-f24e-4c3c-a611-9170c7dcd4db"}}
{"Type": "OrderAccepted", "Data": {"TimeStampUtc": "2018-10-03T23:39:18Z", "OrderId": "7d3a4526-f24e-4c3c-a611-9170c7dcd4db"}}
{"Type": "OrderPlaced", "Data": {"TimeStampUtc": "2018-10-03T23:39:18Z", "OrderId": "bdebe0f4-5eaa-4677-b32b-ad0b6d492f9d"}}
{"Type": "OrderAccepted", "Data": {"TimeStampUtc": "2018-10-03T23:39:18Z", "OrderId": "bdebe0f4-5eaa-4677-b32b-ad0b6d492f9d"}}
{"Type": "OrderPlaced", "Data": {"TimeStampUtc": "2018-10-03T23:39:18Z", "OrderId": "9e898eb0-1c2d-4225-94a7-9f60083f298a"}}
{"Type": "OrderAccepted", "Data": {"TimeStampUtc": "2018-10-03T23:39:18Z", "OrderId": "9e898eb0-1c2d-4225-94a7-9f60083f298a"}}
{"Type": "OrderPlaced", "Data": {"TimeStampUtc": "2018-10-03T23:39:18Z", "OrderId": "9739b3bc-b346-4c65-950b-5977e877f980"}}
{"Type": "OrderAccepted", "Data": {"TimeStampUtc": "2018-10-03T23:39:18Z", "OrderId": "9739b3bc-b346-4c65-950b-5977e877f980"}}
{"Type": "OrderPlaced", "Data": {"TimeStampUtc": "2018-10-03T23:39:18Z", "OrderId": "a5b84bec-7ae4-4098-b972-8385a43cfdf9"}}
{"Type": "OrderAccepted", "Data": {"TimeStampUtc": "2018-10-03T23:39:18Z", "OrderId": "a5b84bec-7ae4-4098-b972-8385a43cfdf9"}}
{"Type": "OrderPlaced", "Data": {"TimeStampUtc": "2018-10-03T23:39:18Z", "OrderId": "3cabacda-f095-4d8e-8d59-627c2683a771"}}
{"Type": "OrderAccepted", "Data": {"TimeStampUtc": "2018-10-03T23:39:18Z", "OrderId": "3cabacda-f095-4d8e-8d59-627c2683a771"}}
{"Type": "OrderPlaced", "Data": {"TimeStampUtc": "2018-10-03T23:39:18Z", "OrderId": "75229e5a-492f-4c6e-905f-c77e2816014c"}}
{"Type": "OrderAccepted", "Data": {"TimeStampUtc": "2018-10-03T23:39:18Z", "OrderId": "75229e5a-492f-4c6e-905f-c77e2816014c"}}
{"Type": "OrderPlaced", "Data": {"TimeStampUtc": "2018-10-03T23:39:18Z", "OrderId": "62c5ff11-5640-46ab-b3d9-00d02d265ceb"}}
{"Type": "OrderAccepted", "Data": {"TimeStampUtc": "2018-10-03T23:39:18Z", "OrderId": "62c5ff11-5640-46ab-b3d9-00d02d265ceb"}}
{"Type": "OrderPlaced", "Data": {"TimeStampUtc": "2018-10-03T23:39:18Z", "OrderId": "c2f32898-41a7-4bed-8301-00c6e0f15b94"}}
{"Type": "OrderAccepted", "Data": {"TimeStampUtc": "2018-10-03T23:39:18Z", "OrderId": "c2f32898-41a7-4bed-8301-00c6e0f15b94"}}
{"Type": "OrderPlaced", "Data": {"TimeStampUtc": "2018-10-03T23:39:18Z", "OrderId": "e49a69aa-e775-46da-b7e6-d7f2e09d1d7a"}}
{"Type": "OrderAccepted", "Data": {"TimeStampUtc": "2018-10-03T23:39:18Z", "OrderId": "e49a69aa-e775-46da-b7e6-d7f2e09d1d7a"}}
{"Type": "OrderPlaced", "Data": {"TimeStampUtc": "2018-10-03T23:39:18Z", "OrderId": "b94e9778-464c-4121-8743-2af188a46eb2"}}
{"Type": "OrderAccepted", "Data": {"TimeStampUtc": "2018-10-03T23:39:18Z", "OrderId": "b94e9778-464c-4121-8743-2af188a46eb2"}}
{"Type": "OrderPlaced", "Data": {"TimeStampUtc": "2018-10-03T23:39:18Z", "OrderId": "6d5c2db9-4ee3-4b28-b7c1-fc86564b6029"}}
{"Type": "OrderAccepted", "Data": {"TimeStampUtc": "2018-10-03T23:39:18Z", "OrderId": "6d5c2db9-4ee3-4b28-b7c1-fc86564b6029"}}
{"Type": "OrderPlaced", "Data": {"TimeStampUtc": "2018-10-03T23:39:18Z", "OrderId": "0de2f159-211f-48f8-9d3b-fe0a4eae40d7"}}
{"Type": "OrderAccepted", "Data": {"TimeStampUtc": "2018-10-03T23:39:18Z", "OrderId": "0de2f159-211f-48f8-9d3b-fe0a4eae40d7"}}
{"Type": "OrderPlaced", "Data": {"TimeStampUtc": "2018-10-03T23:39:18Z", "OrderId": "8589a6fa-8122-44c3-883c-a91887f5049f"}}
{"Type": "OrderAccepted", "Data": {"TimeStampUtc": "2018-10-03T23:39:18Z", "OrderId": "8589a6fa-8122-44c3-883c-a91887f5049f"}}
{"Type": "OrderPlaced", "Data": {"TimeStampUtc": "2018-10-03T23:39:18Z", "OrderId": "f6ba408d-85ae-4da8-9467-d68fb1bb6dfb"}}
{"Type": "OrderAccepted", "Data": {"TimeStampUtc": "2018-10-03T23:39:18Z", "OrderId": "f6ba408d-85ae-4da8-9467-d68fb1bb6dfb"}}
{"Type": "OrderPlaced", "Data": {"TimeStampUtc": "2018-10-03T23:39:18Z", "OrderId": "2eccb96e-bb56-49bd-b7cd-480bd45c6d41"}}
{"Type": "OrderAccepted", "Data": {"TimeStampUtc": "2018-10-03T23:39:18Z", "OrderId": "2eccb96e-bb56-49bd-b7cd-480bd45c6d41"}}
{"Type": "OrderPlaced", "Data": {"TimeStampUtc": "2018-10-03T23:39:18Z", "OrderId": "cb3ee341-9078-4230-8190-1d5edd654934"}}
{"Type": "OrderAccepted", "Data": {"TimeStampUtc": "2018-10-03T23:39:18Z", "OrderId": "cb3ee341-9078-4230-8190-1d5edd654934"}}
{"Type": "OrderPlaced", "Data": {"TimeStampUtc": "2018-10-03T23:39:18Z", "OrderId": "db7eff1a-c39e-47bc-b5f0-62580408fdd6"}}
{"Type": "OrderCancelled", "Data": {"TimeStampUtc": "2018-10-03T23:39:18Z", "OrderId": "db7eff1a-c39e-47bc-b5f0-62580408fdd6"}}
{"Type": "OrderPlaced", "Data": {"TimeStampUtc": "2018-10-03T23:39:18Z", "OrderId": "ef2c7344-cdd7-4365-9827-b43441cb24cb"}}
{"Type": "OrderAccepted", "Data": {"TimeStampUtc": "2018-10-03T23:39:18Z", "OrderId": "ef2c7344-cdd7-4365-9827-b43441cb24cb"}}
{"Type": "OrderPlaced", "Data": {"TimeStampUtc": "2018-10-03T23:39:18Z", "OrderId": "77455ac2-d857-4ef5-95e0-4b9b355e2295"}}
{"Type": "OrderAccepted", "Data": {"TimeStampUtc": "2018-10-03T23:39:18Z", "OrderId": "77455ac2-d857-4ef5-95e0-4b9b355e2295"}}
{"Type": "OrderPlaced", "Data": {"TimeStampUtc": "2018-10-03T23:39:18Z", "OrderId": "66b5dd99-81b6-4ff6-8d0b-fa1761c42682"}}
{"Type": "OrderCancelled", "Data": {"TimeStampUtc": "2018-10-03T23:39:18Z", "OrderId": "66b5dd99-81b6-4ff6-8d0b-fa1761c42682"}}
{"Type": "OrderPlaced", "Data": {"TimeStampUtc": "2018-10-03T23:39:18Z", "OrderId": "44320acd-02b6-4b49-843e-8f2c4586ca17"}}
{"Type": "OrderAccepted", "Data": {"TimeStampUtc": "2018-10-03T23:39:18Z", "OrderId": "44320acd-02b6-4b49-843e-8f2c4586ca17"}}
{"Type": "OrderPlaced", "Data": {"TimeStampUtc": "2018-10-03T23:39:18Z", "OrderId": "3aa76071-19a6-4287-9a07-291f4a49c2a3"}}
{"Type": "OrderAccepted", "Data": {"TimeStampUtc": "2018-10-03T23:39:18Z", "OrderId": "3aa76071-19a6-4287-9a07-291f4a49c2a3"}}
{"Type": "OrderPlaced", "Data": {"TimeStampUtc": "2018-10-03T23:39:18Z", "OrderId": "3547d747-84d9-4a21-baf6-168643c47526"}}
{"Type": "OrderCancelled", "Data": {"TimeStampUtc": "2018-10-03T23:39:18Z", "OrderId": "3547d747-84d9-4a21-baf6-168643c47526"}}
