{"Type": "OrderPlaced", "Data": {"TimeStampUtc": "2018-10-03T23:39:02Z", "OrderId": "7848f838-5fde-4aba-ba84-daad14a86865"}}
{"Type": "OrderAccepted", "Data": {"TimeStampUtc": "2018-10-03T23:39:02Z", "OrderId": "7848f838-5fde-4aba-ba84-daad14a86865"}}
{"Type": "OrderPlaced", "Data": {"TimeStampUtc": "2018-10-03T23:39:02Z", "OrderId": "84c0bf28-1c39-41cc-a06d-e88d4b9a0e51"}}
{"Type": "OrderAccepted", "Data": {"TimeStampUtc": "2018-10-03T23:39:02Z", "OrderId": "84c0bf28-1c39-41cc-a06d-e88d4b9a0e51"}}
{"Type": "OrderPlaced", "Data": {"TimeStampUtc": "2018-10-03T23:39:02Z", "OrderId": "d09a6b74-dc24-48a4-b41c-c73260cddf21"}}
{"Type": "OrderAccepted", "Data": {"TimeStampUtc": "2018-10-03T23:39:02Z", "OrderId": "d09a6b74-dc24-48a4-b41c-c73260cddf21"}}
{"Type": "OrderPlaced", "Data": {"TimeStampUtc": "2018-10-03T23:39:02Z", "OrderId": "08c23fb1-8cf0-4099-ba89-d90081705a66"}}
{"Type": "OrderAccepted", "Data": {"TimeStampUtc": "2018-10-03T23:39:02Z", "OrderId": "08c23fb1-8cf0-4099-ba89-d90081705a66"}}
{"Type": "OrderPlaced", "Data": {"TimeStampUtc": "2018-10-03T23:39:02Z", "OrderId": "881965d0-8962-4393-9517-247ff9a7f477"}}
{"Type": "OrderAccepted", "Data": {"TimeStampUtc": "2018-10-03T23:39:02Z", "OrderId": "881965d0-8962-4393-9517-247ff9a7f477"}}
{"Type": "OrderPlaced", "Data": {"TimeStampUtc": "2018-10-03T23:39:02Z", "OrderId": "3b7fa099-ad94-428e-ac7c-8e29451df44f"}}
{"Type": "OrderAccepted", "Data": {"TimeStampUtc": "2018-10-03T23:39:02Z", "OrderId": "3b7fa099-ad94-428e-ac7c-8e29451df44f"}}
{"Type": "OrderPlaced", "Data": {"TimeStampUtc": "2018-10-03T23:39:02Z", "OrderId": "951888f5-e815-46e4-a363-848ccc974a47"}}
{"Type": "OrderAccepted", "Data": {"TimeStampUtc": "2018-10-03T23:39:02Z", "OrderId": "951888f5-e815-46e4-a363-848ccc974a47"}}
{"Type": "OrderPlaced", "Data": {"TimeStampUtc": "2018-10-03T23:39:02Z", "OrderId": "515dcbf4-8fc8-436f-8620-9b48146a18c8"}}
{"Type": "OrderAccepted", "Data": {"TimeStampUtc": "2018-10-03T23:39:02Z", "OrderId": "515dcbf4-8fc8-436f-8620-9b48146a18c8"}}
{"Type": "OrderPlaced", "Data": {"TimeStampUtc": "2018-10-03T23:39:02Z", "OrderId": "c077ec9f-7ffe-40a8-afaa-f744af689e93"}}
{"Type": "OrderAccepted", "Data": {"TimeStampUtc": "2018-10-03T23:39:02Z", "OrderId": "c077ec9f-7ffe-40a8-afaa-f744af689e93"}}
{"Type": "OrderPlaced", "Data": {"TimeStampUtc": "2018-10-03T23:39:02Z", "OrderId": "193e3b19-0cfe-4f97-8a90-ad171f534a5c"}}
{"Type": "OrderAccepted", "Data": {"TimeStampUtc": "2018-10-03T23:39:02Z", "OrderId": "193e3b19-0cfe-4f97-8a90-ad171f534a5c"}}
{"Type": "OrderPlaced", "Data": {"TimeStampUtc": "2018-10-03T23:39:02Z", "OrderId": "983c2511-d10f-4a0e-90a4-1a460557c0ab"}}
{"Type": "OrderCancelled", "Data": {"TimeStampUtc": "2018-10-03T23:39:02Z", "OrderId": "983c2511-d10f-4a0e-90a4-1a460557c0ab"}}
{"Type": "OrderPlaced", "Data": {"TimeStampUtc": "2018-10-03T23:39:02Z", "OrderId": "c429a084-b36d-4c36-afe0-a92adf7f31fd"}}
{"Type": "OrderAccepted", "Data": {"TimeStampUtc": "2018-10-03T23:39:02Z", "OrderId": "c429a084-b36d-4c36-afe0-a92adf7f31fd"}}
{"Type": "OrderPlaced", "Data": {"TimeStampUtc": "2018-10-03T23:39:02Z", "OrderId": "8c25fed0-074b-42b0-8e93-73734bebc277"}}
{"Type": "OrderAccepted", "Data": {"TimeStampUtc": "2018-10-03T23:39:02Z", "OrderId": "8c25fed0-074b-42b0-8e93-73734bebc277"}}
{"Type": "OrderPlaced", "Data": {"TimeStampUtc": "2018-10-03T23:39:02Z", "OrderId": "b28e821c-4938-4469-9e4a-b39a44fc94a2"}}
{"Type": "OrderAccepted", "Data": {"TimeStampUtc": "2018-10-03T23:39:02Z", "OrderId": "b28e821c-4938-4469-9e4a-b39a44fc94a2"}}
{"Type": "OrderPlaced", "Data": {"TimeStampUtc": "2018-10-03T23:39:02Z", "OrderId": "1939caa9-60ea-44fb-b309-a4007cd8e8e0"}}
{"Type": "OrderAccepted", "Data": {"TimeStampUtc": "2018-10-03T23:39:02Z", "OrderId": "1939caa9-60ea-44fb-b309-a4007cd8e8e0"}}
{"Type": "OrderPlaced", "Data": {"TimeStampUtc": "2018-10-03T23:39:02Z", "OrderId": "e2509dbf-58b8-4a14-8aae-20746b1ecb0c"}}
{"Type": "OrderAccepted", "Data": {"TimeStampUtc": "2018-10-03T23:39:02Z", "OrderId": "e2509dbf-58b8-4a14-8aae-20746b1ecb0c"}}
{"Type": "OrderPlaced", "Data": {"TimeStampUtc": "2018-10-03T23:39:02Z", "OrderId": "96566959-e773-4c23-9b73-bd1a955334f7"}}
{"Type": "OrderAccepted", "Data": {"TimeStampUtc": "2018-10-03T23:39:02Z", "OrderId": "96566959-e773-4c23-9b73-bd1a955334f7"}}
{"Type": "OrderPlaced", "Data": {"TimeStampUtc": "2018-10-03T23:39:02Z", "OrderId": "f82938ae-1fb1-482b-a8bc-f68c464b38c3"}}
{"Type": "OrderAccepted", "Data": {"TimeStampUtc": "2018-10-03T23:39:02Z", "OrderId": "f82938ae-1fb1-482b-a8bc-f68c464b38c3"}}
{"Type": "OrderPlaced", "Data": {"TimeStampUtc": "2018-10-03T23:39:02Z", "OrderId": "d46c1fc4-ecc6-4d73-b35e-4f2f5e498c28"}}
{"Type": "OrderAccepted", "Data": {"TimeStampUtc": "2018-10-03T23:39:02Z", "OrderId": "d46c1fc4-ecc6-4d73-b35e-4f2f5e498c28"}}
{"Type": "OrderPlaced", "Data": {"TimeStampUtc": "2018-10-03T23:39:02Z", "OrderId": "f17d7f5c-c5cd-4802-8bea-913fc420ece6"}}
{"Type": "OrderAccepted", "Data": {"TimeStampUtc": "2018-10-03T23:39:02Z", "OrderId": "f17d7f5c-c5cd-4802-8bea-913fc420ece6"}}
{"Type": "OrderPlaced", "Data": {"TimeStampUtc": "2018-10-03T23:39:02Z", "OrderId": "ce064c70-5119-4ac9-a91a-d12bfd300afb"}}
{"Type": "OrderAccepted", "Data": {"TimeStampUtc": "2018-10-03T23:39:02Z", "OrderId": "ce064c70-5119-4ac9-a91a-d12bfd300afb"}}
{"Type": "OrderPlaced", "Data": {"TimeStampUtc": "2018-10-03T23:39:02Z", "OrderId": "7ede0276-ea4f-428f-9460-ff7ee180ae5d"}}
{"Type": "OrderCancelled", "Data": {"TimeStampUtc": "2018-10-03T23:39:02Z", "OrderId": "7ede0276-ea4f-428f-9460-ff7ee180ae5d"}}
{"Type": "OrderPlaced", "Data": {"TimeStampUtc": "2018-10-03T23:39:02Z", "OrderId": "6591ee6f-ace7-4e62-88fb-7ee02e30ae34"}}
{"Type": "OrderCancelled", "Data": {"TimeStampUtc": "2018-10-03T23:39:02Z", "OrderId": "6591ee6f-ace7-4e62-88fb-7ee02e30ae34"}}
{"Type": "OrderPlaced", "Data": {"TimeStampUtc": "2018-10-03T23:39:02Z", "OrderId": "17849aad-509b-466b-bfdf-e825eb170589"}}
{"Type": "OrderCancelled", "Data": {"TimeStampUtc": "2018-10-03T23:39:02Z", "OrderId": "17849aad-509b-466b-bfdf-e825eb170589"}}
{"Type": "OrderPlaced", "Data": {"TimeStampUtc": "2018-10-03T23:39:02Z", "OrderId": "ab061fc5-4c17-40e3-8cc2-48ce0c8d4fe3"}}
{"Type": "OrderAccepted", "Data": {"TimeStampUtc": "2018-10-03T23:39:02Z", "OrderId": "ab061fc5-4c17-40e3-8cc2-48ce0c8d4fe3"}}
{"Type": "OrderPlaced", "Data": {"TimeStampUtc": "2018-10-03T23:39:02Z", "OrderId": "860c2463-9fff-481c-9d8f-3272a8e6ceee"}}
{"Type": "OrderAccepted", "Data": {"TimeStampUtc": "2018-10-03T23:39:02Z", "OrderId": "860c2463-9fff-481c-9d8f-3272a8e6ceee"}}
{"Type": "OrderPlaced", "Data": {"TimeStampUtc": "2018-10-03T23:39:02Z", "OrderId": "85b0c9cf-51b8-44c5-811f-1d527290dd20"}}
{"Type": "OrderAccepted", "Data": {"TimeStampUtc": "2018-10-03T23:39:02Z", "OrderId": "85b0c9cf-51b8-44c5-811f-1d527290dd20"}}
{"Type": "OrderPlaced", "Data": {"TimeStampUtc": "2018-10-03T23:39:02Z", "OrderId": "d7bffb6e-9d4a-4f3c-a9ef-96b367443ed8"}}
{"Type": "OrderAccepted", "Data": {"TimeStampUtc": "2018-10-03T23:39:02Z", "OrderId": "d7bffb6e-9d4a-4f3c-a9ef-96b367443ed8"}}
{"Type": "OrderPlaced", "Data": {"TimeStampUtc": "2018-10-03T23:39:02Z", "OrderId": "d13c6b95-987b-4121-9bd9-bcd605e82d73"}}
{"Type": "OrderAccepted", "Data": {"TimeStampUtc": "2018-10-03T23:39:02Z", "OrderId": "d13c6b95-987b-4121-9bd9-bcd605e82d73"}}
{"Type": "OrderPlaced", "Data": {"TimeStampUtc": "2018-10-03T23:39:02Z", "OrderId": "7632c427-05a8-4020-be1b-26b5b092ee75"}}
{"Type": "OrderAccepted", "Data": {"TimeStampUtc": "2018-10-03T23:39:02Z", "OrderId": "7632c427-05a8-4020-be1b-26b5b092ee75"}}
{"Type": "OrderPlaced", "Data": {"TimeStampUtc": "2018-10-03T23:39:02Z", "OrderId": "2996eb79-4d3c-40b7-8ef7-52f6ecfa7ff5"}}
{"Type": "OrderAccepted", "Data": {"TimeStampUtc": "2018-10-03T23:39:02Z", "OrderId": "2996eb79-4d3c-40b7-8ef7-52f6ecfa7ff5"}}
{"Type": "OrderPlaced", "Data": {"TimeStampUtc": "2018-10-03T23:39:02Z", "OrderId": "1b54d001-ae36-4ca8-b6ff-42be92b57be5"}}
{"Type": "OrderAccepted", "Data": {"TimeStampUtc": "2018-10-03T23:39:02Z", "OrderId": "1b54d001-ae36-4ca8-b6ff-42be92b57be5"}}
{"Type": "OrderPlaced", "Data": {"TimeStampUtc": "2018-10-03T23:39:02Z", "OrderId": "7c1a351a-5e31-47ff-a829-a28dc97cecac"}}
{"Type": "OrderAccepted", "Data": {"TimeStampUtc": "2018-10-03T23:39:02Z", "OrderId": "7c1a351a-5e31-47ff-a829-a28dc97cecac"}}
{"Type": "OrderPlaced", "Data": {"TimeStampUtc": "2018-10-03T23:39:02Z", "OrderId": "85cbaa11-49fc-4256-8c2e-825700ef1be1"}}
{"Type": "OrderAccepted", "Data": {"TimeStampUtc": "2018-10-03T23:39:02Z", "OrderId": "85cbaa11-49fc-4256-8c2e-825700ef1be1"}}
{"Type": "OrderPlaced", "Data": {"TimeStampUtc": "2018-10-03T23:39:02Z", "OrderId": "69ef8343-246b-4a83-9775-fd22bcec7173"}}
{"Type": "OrderAccepted", "Data": {"TimeStampUtc": "2018-10-03T23:39:02Z", "OrderId": "69ef8343-246b-4a83-9775-fd22bcec7173"}}
{"Type": "OrderPlaced", "Data": {"TimeStampUtc": "2018-10-03T23:39:02Z", "OrderId": "df26b0da-b609-4151-ad95-bf4927646150"}}
{"Type": "OrderAccepted", "Data": {"TimeStampUtc": "2018-10-03T23:39:02Z", "OrderId": "df26b0da-b609-4151-ad95-bf4927646150"}}
{"Type": "OrderPlaced", "Data": {"TimeStampUtc": "2018-10-03T23:39:02Z", "OrderId": "3e9bd75e-0abd-4b0b-9e37-5d200df90206"}}
{"Type": "OrderAccepted", "Data": {"TimeStampUtc": "2018-10-03T23:39:02Z", "OrderId": "3e9bd75e-0abd-4b0b-9e37-5d200df90206"}}
{"Type": "OrderPlaced", "Data": {"TimeStampUtc": "2018-10-03T23:39:02Z", "OrderId": "80ba4af8-5528-4d2a-ae2a-176649cd75ed"}}
{"Type": "OrderAccepted", "Data": {"TimeStampUtc": "2018-10-03T23:39:02Z", "OrderId": "80ba4af8-5528-4d2a-ae2a-176649cd75ed"}}
{"Type": "OrderPlaced", "Data": {"TimeStampUtc": "2018-10-03T23:39:02Z", "OrderId": "01a2f5e0-8931-4654-b383-9faf7a2a1dff"}}
{"Type": "OrderAccepted", "Data": {"TimeStampUtc": "2018-10-03T23:39:02Z", "OrderId": "01a2f5e0-8931-4654-b383-9faf7a2a1dff"}}
{"Type": "OrderPlaced", "Data": {"TimeStampUtc": "2018-10-03T23:39:02Z", "OrderId": "c09fdfc0-4fe5-43f4-b216-f35e510de5c7"}}
{"Type": "OrderAccepted", "Data": {"TimeStampUtc": "2018-10-03T23:39:02Z", "OrderId": "c09fdfc0-4fe5-43f4-b216-f35e510de5c7"}}
{"Type": "OrderPlaced", "Data": {"TimeStampUtc": "2018-10-03T23:39:02Z", "OrderId": "0c51c276-b352-4dd7-a3a8-07930a9f937e"}}
{"Type": "OrderAccepted", "Data": {"TimeStampUtc": "2018-10-03T23:39:02Z", "OrderId": "0c51c276-b352-4dd7-a3a8-07930a9f937e"}}
{"Type": "OrderPlaced", "Data": {"TimeStampUtc": "2018-10-03T23:39:02Z", "OrderId": "ca6fc65f-7246-4271-abf0-41f630d905fb"}}
{"Type": "OrderAccepted", "Data": {"TimeStampUtc": "2018-10-03T23:39:02Z", "OrderId": "ca6fc65f-7246-4271-abf0-41f630d905fb"}}
{"Type": "OrderPlaced", "Data": {"TimeStampUtc": "2018-10-03T23:39:02Z", "OrderId": "1b39992d-a650-45e0-8865-9a71c508d99f"}}
{"Type": "OrderCancelled", "Data": {"TimeStampUtc": "2018-10-03T23:39:02Z", "OrderId": "1b39992d-a650-45e0-8865-9a71c508d99f"}}
{"Type": "OrderPlaced", "Data": {"TimeStampUtc": "2018-10-03T23:39:02Z", "OrderId": "6c187a44-ccca-4e0a-8620-1e2ae70b0a5d"}}
{"Type": "OrderAccepted", "Data": {"TimeStampUtc": "2018-10-03T23:39:02Z", "OrderId": "6c187a44-ccca-4e0a-8620-1e2ae70b0a5d"}}
{"Type": "OrderPlaced", "Data": {"TimeStampUtc": "2018-10-03T23:39:02Z", "OrderId": "dd5068ef-12f3-41af-88c3-3d9ed753f502"}}
{"Type": "OrderAccepted", "Data": {"TimeStampUtc": "2018-10-03T23:39:02Z", "OrderId": "dd5068ef-12f3-41af-88c3-3d9ed753f502"}}
{"Type": "OrderPlaced", "Data": {"TimeStampUtc": "2018-10-03T23:39:02Z", "OrderId": "be937d07-a4e9-48bf-9299-ab82e6a80ed7"}}
{"Type": "OrderAccepted", "Data": {"TimeStampUtc": "2018-10-03T23:39:02Z", "OrderId": "be937d07-a4e9-48bf-9299-ab82e6a80ed7"}}
{"Type": "OrderPlaced", "Data": {"TimeStampUtc": "2018-10-03T23:39:02Z", "OrderId": "777c1999-97d5-4635-97e9-fbc9602fea63"}}
{"Type": "OrderAccepted", "Data": {"TimeStampUtc": "2018-10-03T23:39:02Z", "OrderId": "777c1999-97d5-4635-97e9-fbc9602fea63"}}
{"Type": "OrderPlaced", "Data": {"TimeStampUtc": "2018-10-03T23:39:02Z", "OrderId": "9874a957-21fe-480f-84ec-8198aa086d85"}}
{"Type": "OrderCancelled", "Data": {"TimeStampUtc": "2018-10-03T23:39:02Z", "OrderId": "9874a957-21fe-480f-84ec-8198aa086d85"}}
{"Type": "OrderPlaced", "Data": {"TimeStampUtc": "2018-10-03T23:39:02Z", "OrderId": "6e565fce-164d-4aaa-b91a-02a2844daeb4"}}
{"Type": "OrderAccepted", "Data": {"TimeStampUtc": "2018-10-03T23:39:02Z", "OrderId": "6e565fce-164d-4aaa-b91a-02a2844daeb4"}}
{"Type": "OrderPlaced", "Data": {"TimeStampUtc": "2018-10-03T23:39:02Z", "OrderId": "ff7ddcd9-3f30-444f-a494-a8e860e93e1e"}}
{"Type": "OrderAccepted", "Data": {"TimeStampUtc": "2018-10-03T23:39:02Z", "OrderId": "ff7ddcd9-3f30-444f-a494-a8e860e93e1e"}}
{"Type": "OrderPlaced", "Data": {"TimeStampUtc": "2018-10-03T23:39:02Z", "OrderId": "c8c70ed8-6d50-4569-a819-e1f3d3cc9ff2"}}
{"Type": "OrderAccepted", "Data": {"TimeStampUtc": "2018-10-03T23:39:02Z", "OrderId": "c8c70ed8-6d50-4569-a819-e1f3d3cc9ff2"}}
{"Type": "OrderPlaced", "Data": {"TimeStampUtc": "2018-10-03T23:39:02Z", "OrderId": "5ac14e92-f26a-4673-abf6-29e447072305"}}
{"Type": "OrderAccepted", "Data": {"TimeStampUtc": "2018-10-03T23:39:02Z", "OrderId": "5ac14e92-f26a-4673-abf6-29e447072305"}}
{"Type": "OrderPlaced", "Data": {"TimeStampUtc": "2018-10-03T23:39:02Z", "OrderId": "7adca91a-64f3-44dd-96cd-a0b54cab7f2e"}}
{"Type": "OrderAccepted", "Data": {"TimeStampUtc": "2018-10-03T23:39:02Z", "OrderId": "7adca91a-64f3-44dd-96cd-a0b54cab7f2e"}}
{"Type": "OrderPlaced", "Data": {"TimeStampUtc": "2018-10-03T23:39:02Z", "OrderId": "f71be4af-e013-4904-945b-2aafb041182b"}}
{"Type": "OrderAccepted", "Data": {"TimeStampUtc": "2018-10-03T23:39:02Z", "OrderId": "f71be4af-e013-4904-945b-2aafb041182b"}}
{"Type": "OrderPlaced", "Data": {"TimeStampUtc": "2018-10-03T23:39:02Z", "OrderId": "db090ea6-85fe-4e92-af41-df576ef46938"}}
{"Type": "OrderCancelled", "Data": {"TimeStampUtc": "2018-10-03T23:39:02Z", "OrderId": "db090ea6-85fe-4e92-af41-df576ef46938"}}
{"Type": "OrderPlaced", "Data": {"TimeStampUtc": "2018-10-03T23:39:02Z", "OrderId": "8b0400a4-1113-43e7-9b8f-7a44f87f9b50"}}
{"Type": "OrderCancelled", "Data": {"TimeStampUtc": "2018-10-03T23:39:02Z", "OrderId": "8b0400a4-1113-43e7-9b8f-7a44f87f9b50"}}
{"Type": "OrderPlaced", "Data": {"TimeStampUtc": "2018-10-03T23:39:02Z", "OrderId": "5ea36cac-e4c2-4752-958a-a9719c08527d"}}
{"Type": "OrderCancelled", "Data": {"TimeStampUtc": "2018-10-03T23:39:02Z", "OrderId": "5ea36cac-e4c2-4752-958a-a9719c08527d"}}
{"Type": "OrderPlaced", "Data": {"TimeStampUtc": "2018-10-03T23:39:02Z", "OrderId": "9f6f88fe-36a8-4a39-875b-31adfb209453"}}
{"Type": "OrderAccepted", "Data": {"TimeStampUtc": "2018-10-03T23:39:02Z", "OrderId": "9f6f88fe-36a8-4a39-875b-31adfb209453"}}
{"Type": "OrderPlaced", "Data": {"TimeStampUtc": "2018-10-03T23:39:02Z", "OrderId": "000c91af-88e1-44a6-9174-07753d32af87"}}
{"Type": "OrderCancelled", "Data": {"TimeStampUtc": "2018-10-03T23:39:02Z", "OrderId": "000c91af-88e1-44a6-9174-07753d32af87"}}
{"Type": "OrderPlaced", "Data": {"TimeStampUtc": "2018-10-03T23:39:02Z", "OrderId": "fc491b51-b901-4916-8dee-8176cc0f3d98"}}
{"Type": "OrderAccepted", "Data": {"TimeStampUtc": "2018-10-03T23:39:02Z", "OrderId": "fc491b51-b901-4916-8dee-8176cc0f3d98"}}
{"Type": "OrderPlaced", "Data": {"TimeStampUtc": "2018-10-03T23:39:02Z", "OrderId": "fe34f202-41ff-408c-928f-9edacdadb065"}}
{"Type": "OrderAccepted", "Data": {"TimeStampUtc": "2018-10-03T23:39:02Z", "OrderId": "fe34f202-41ff-408c-928f-9edacdadb065"}}
{"Type": "OrderPlaced", "Data": {"TimeStampUtc": "2018-10-03T23:39:02Z", "OrderId": "85381426-0e78-40e8-9e25-b82b7e0a5405"}}
{"Type": "OrderAccepted", "Data": {"TimeStampUtc": "2018-10-03T23:39:02Z", "OrderId": "85381426-0e78-40e8-9e25-b82b7e0a5405"}}
{"Type": "OrderPlaced", "Data": {"TimeStampUtc": "2018-10-03T23:39:02Z", "OrderId": "57b6be53-9138-41b8-8165-141efe8a93fe"}}
{"Type": "OrderAccepted", "Data": {"TimeStampUtc": "2018-10-03T23:39:02Z", "OrderId": "57b6be53-9138-41b8-8165-141efe8a93fe"}}
{"Type": "OrderPlaced", "Data": {"TimeStampUtc": "2018-10-03T23:39:02Z", "OrderId": "45fce558-0626-4ed6-b608-4d9b85685982"}}
{"Type": "OrderAccepted", "Data": {"TimeStampUtc": "2018-10-03T23:39:02Z", "OrderId": "45fce558-0626-4ed6-b608-4d9b85685982"}}
{"Type": "OrderPlaced", "Data": {"TimeStampUtc": "2018-10-03T23:39:02Z", "OrderId": "099bcd52-729a-4dff-9b96-bdfee8647364"}}
{"Type": "OrderAccepted", "Data": {"TimeStampUtc": "2018-10-03T23:39:02Z", "OrderId": "099bcd52-729a-4dff-9b96-bdfee8647364"}}
{"Type": "OrderPlaced", "Data": {"TimeStampUtc": "2018-10-03T23:39:02Z", "OrderId": "ef6324aa-28ba-4e2d-b61e-2d25200d4f99"}}
{"Type": "OrderAccepted", "Data": {"TimeStampUtc": "2018-10-03T23:39:02Z", "OrderId": "ef6324aa-28ba-4e2d-b61e-2d25200d4f99"}}
{"Type": "OrderPlaced", "Data": {"TimeStampUtc": "2018-10-03T23:39:02Z", "OrderId": "a73762c1-07ef-448c-a3f0-5ae7c1b6741b"}}
{"Type": "OrderCancelled", "Data": {"TimeStampUtc": "2018-10-03T23:39:02Z", "OrderId": "a73762c1-07ef-448c-a3f0-5ae7c1b6741b"}}
{"Type": "OrderPlaced", "Data": {"TimeStampUtc": "2018-10-03T23:39:02Z", "OrderId": "4adff201-8efe-4103-8b54-8345251cce82"}}
{"Type": "OrderAccepted", "Data": {"TimeStampUtc": "2018-10-03T23:39:02Z", "OrderId": "4adff201-8efe-4103-8b54-8345251cce82"}}
{"Type": "OrderPlaced", "Data": {"TimeStampUtc": "2018-10-03T23:39:02Z", "OrderId": "3f45f466-bff9-4c19-a3b0-1f39c91aa269"}}
{"Type": "OrderAccepted", "Data": {"TimeStampUtc": "2018-10-03T23:39:02Z", "OrderId": "3f45f466-bff9-4c19-a3b0-1f39c91aa269"}}
{"Type": "OrderPlaced", "Data": {"TimeStampUtc": "2018-10-03T23:39:02Z", "OrderId": "cef6013c-224a-4b8f-9daf-a297e66ca2c9"}}
{"Type": "OrderAccepted", "Data": {"TimeStampUtc": "2018-10-03T23:39:02Z", "OrderId": "cef6013c-224a-4b8f-9daf-a297e66ca2c9"}}
{"Type": "OrderPlaced", "Data": {"TimeStampUtc": "2018-10-03T23:39:02Z", "OrderId": "4d4f896f-8b1c-4c3f-892b-b650f491ba1c"}}
{"Type": "OrderAccepted", "Data": {"TimeStampUtc": "2018-10-03T23:39:02Z", "OrderId": "4d4f896f-8b1c-4c3f-892b-b650f491ba1c"}}
{"Type": "OrderPlaced", "Data": {"TimeStampUtc": "2018-10-03T23:39:02Z", "OrderId": "10d28cb5-8ce7-4176-9a88-2ef0da6e892e"}}
{"Type": "OrderAccepted", "Data": {"TimeStampUtc": "2018-10-03T23:39:02Z", "OrderId": "10d28cb5-8ce7-4176-9a88-2ef0da6e892e"}}
{"Type": "OrderPlaced", "Data": {"TimeStampUtc": "2018-10-03T23:39:02Z", "OrderId": "e3241ab7-ccff-4ccb-a598-d9d726a2e08d"}}
{"Type": "OrderAccepted", "Data": {"TimeStampUtc": "2018-10-03T23:39:02Z", "OrderId": "e3241ab7-ccff-4ccb-a598-d9d726a2e08d"}}
{"Type": "OrderPlaced", "Data": {"TimeStampUtc": "2018-10-03T23:39:02Z", "OrderId": "cb0b0e63-0fb3-4101-9dd8-1c0409b96a8d"}}
{"Type": "OrderCancelled", "Data": {"TimeStampUtc": "2018-10-03T23:39:02Z", "OrderId": "cb0b0e63-0fb3-4101-9dd8-1c0409b96a8d"}}
{"Type": "OrderPlaced", "Data": {"TimeStampUtc": "2018-10-03T23:39:02Z", "OrderId": "0bda4b07-da9c-4b2d-812f-313be4a5c1a7"}}
{"Type": "OrderCancelled", "Data": {"TimeStampUtc": "2018-10-03T23:39:02Z", "OrderId": "0bda4b07-da9c-4b2d-812f-313be4a5c1a7"}}
{"Type": "OrderPlaced", "Data": {"TimeStampUtc": "2018-10-03T23:39:02Z", "OrderId": "2e2c67af-c5a8-4b24-9846-7a6d0e4da14d"}}
{"Type": "OrderCancelled", "Data": {"TimeStampUtc": "2018-10-03T23:39:02Z", "OrderId": "2e2c67af-c5a8-4b24-9846-7a6d0e4da14d"}}
{"Type": "OrderPlaced", "Data": {"TimeStampUtc": "2018-10-03T23:39:02Z", "OrderId": "d2a6aa02-add4-46c0-81cc-5abf9f6209ac"}}
{"Type": "OrderAccepted", "Data": {"TimeStampUtc": "2018-10-03T23:39:02Z", "OrderId": "d2a6aa02-add4-46c0-81cc-5abf9f6209ac"}}
{"Type": "OrderPlaced", "Data": {"TimeStampUtc": "2018-10-03T23:39:02Z", "OrderId": "6eccd7d9-7877-4bb8-a223-a9b881d97440"}}
{"Type": "OrderAccepted", "Data": {"TimeStampUtc": "2018-10-03T23:39:02Z", "OrderId": "6eccd7d9-7877-4bb8-a223-a9b881d97440"}}
{"Type": "OrderPlaced", "Data": {"TimeStampUtc": "2018-10-03T23:39:02Z", "OrderId": "71e73c03-c46c-4d2b-a65b-e26918c7f1f9"}}
{"Type": "OrderAccepted", "Data": {"TimeStampUtc": "2018-10-03T23:39:02Z", "OrderId": "71e73c03-c46c-4d2b-a65b-e26918c7f1f9"}}
{"Type": "OrderPlaced", "Data": {"TimeStampUtc": "2018-10-03T23:39:02Z", "OrderId": "cdc69cb0-293a-4e08-a90b-d1f6cd796b5a"}}
{"Type": "OrderAccepted", "Data": {"TimeStampUtc": "2018-10-03T23:39:02Z", "OrderId": "cdc69cb0-293a-4e08-a90b-d1f6cd796b5a"}}
{"Type": "OrderPlaced", "Data": {"TimeStampUtc": "2018-10-03T23:39:02Z", "OrderId": "a52cda6c-4f39-4247-8b13-49dd7a9f6e3a"}}
{"Type": "OrderAccepted", "Data": {"TimeStampUtc": "2018-10-03T23:39:02Z", "OrderId": "a52cda6c-4f39-4247-8b13-49dd7a9f6e3a"}}
{"Type": "OrderPlaced", "Data": {"TimeStampUtc": "2018-10-03T23:39:02Z", "OrderId": "89ea4649-37bb-4600-a9c4-8bb197595cb2"}}
{"Type": "OrderAccepted", "Data": {"TimeStampUtc": "2018-10-03T23:39:02Z", "OrderId": "89ea4649-37bb-4600-a9c4-8bb197595cb2"}}
{"Type": "OrderPlaced", "Data": {"TimeStampUtc": "2018-10-03T23:39:02Z", "OrderId": "84b1bb85-67e8-4c23-8884-9ac468f2e28f"}}
{"Type": "OrderAccepted", "Data": {"TimeStampUtc": "2018-10-03T23:39:02Z", "OrderId": "84b1bb85-67e8-4c23-8884-9ac468f2e28f"}}
{"Type": "OrderPlaced", "Data": {"TimeStampUtc": "2018-10-03T23:39:02Z", "OrderId": "2458ec5c-b72c-4fab-85a8-4cf6ea1dd25f"}}
{"Type": "OrderAccepted", "Data": {"TimeStampUtc": "2018-10-03T23:39:02Z", "OrderId": "2458ec5c-b72c-4fab-85a8-4cf6ea1dd25f"}}
{"Type": "OrderPlaced", "Data": {"TimeStampUtc": "2018-10-03T23:39:02Z", "OrderId": "7895dce8-9916-4997-89f8-d8606a5e07a2"}}
{"Type": "OrderCancelled", "Data": {"TimeStampUtc": "2018-10-03T23:39:02Z", "OrderId": "7895dce8-9916-4997-89f8-d8606a5e07a2"}}
{"Type": "OrderPlaced", "Data": {"TimeStampUtc": "2018-10-03T23:39:02Z", "OrderId": "76f3c8a8-7aa0-4244-8287-32c18dcd29a0"}}
{"Type": "OrderCancelled", "Data": {"TimeStampUtc": "2018-10-03T23:39:02Z", "OrderId": "76f3c8a8-7aa0-4244-8287-32c18dcd29a0"}}
{"Type": "OrderPlaced", "Data": {"TimeStampUtc": "2018-10-03T23:39:02Z", "OrderId": "126ff5e0-a9e6-47cb-af53-e586d9f07536"}}
{"Type": "OrderAccepted", "Data": {"TimeStampUtc": "2018-10-03T23:39:02Z", "OrderId": "126ff5e0-a9e6-47cb-af53-e586d9f07536"}}
{"Type": "OrderPlaced", "Data": {"TimeStampUtc": "2018-10-03T23:39:02Z", "OrderId": "35aee0e4-5442-4d83-837c-7371e3b3da15"}}
{"Type": "OrderAccepted", "Data": {"TimeStampUtc": "2018-10-03T23:39:02Z", "OrderId": "35aee0e4-5442-4d83-837c-7371e3b3da15"}}
{"Type": "OrderPlaced", "Data": {"TimeStampUtc": "2018-10-03T23:39:02Z", "OrderId": "120858fd-5e23-477f-a432-2830ad3e801b"}}
{"Type": "OrderAccepted", "Data": {"TimeStampUtc": "2018-10-03T23:39:02Z", "OrderId": "120858fd-5e23-477f-a432-2830ad3e801b"}}
{"Type": "OrderPlaced", "Data": {"TimeStampUtc": "2018-10-03T23:39:02Z", "OrderId": "b2584f78-2b53-4c4a-8701-6e4596f6ccd1"}}
{"Type": "OrderAccepted", "Data": {"TimeStampUtc": "2018-10-03T23:39:02Z", "OrderId": "b2584f78-2b53-4c4a-8701-6e4596f6ccd1"}}
{"Type": "OrderPlaced", "Data": {"TimeStampUtc": "2018-10-03T23:39:02Z", "OrderId": "896c7739-201b-4265-b502-78ab4b18fe0c"}}
{"Type": "OrderAccepted", "Data": {"TimeStampUtc": "2018-10-03T23:39:02Z", "OrderId": "896c7739-201b-4265-b502-78ab4b18fe0c"}}
{"Type": "OrderPlaced", "Data": {"TimeStampUtc": "2018-10-03T23:39:02Z", "OrderId": "fc3f6d42-ee00-423a-ad73-2a65fbba00cc"}}
{"Type": "OrderAccepted", "Data": {"TimeStampUtc": "2018-10-03T23:39:02Z", "OrderId": "fc3f6d42-ee00-423a-ad73-2a65fbba00cc"}}
{"Type": "OrderPlaced", "Data": {"TimeStampUtc": "2018-10-03T23:39:02Z", "OrderId": "2488d211-998a-47a0-8a7a-d8861ad894c4"}}
{"Type": "OrderAccepted", "Data": {"TimeStampUtc": "2018-10-03T23:39:02Z", "OrderId": "2488d211-998a-47a0-8a7a-d8861ad894c4"}}
{"Type": "OrderPlaced", "Data": {"TimeStampUtc": "2018-10-03T23:39:02Z", "OrderId": "02a54204-31e9-41c2-9d40-98d030e12a43"}}
{"Type": "OrderAccepted", "Data": {"TimeStampUtc": "2018-10-03T23:39:02Z", "OrderId": "02a54204-31e9-41c2-9d40-98d030e12a43"}}
{"Type": "OrderPlaced", "Data": {"TimeStampUtc": "2018-10-03T23:39:02Z", "OrderId": "b120595a-f67b-4f05-8ba1-b2c77721f24e"}}
{"Type": "OrderAccepted", "Data": {"TimeStampUtc": "2018-10-03T23:39:02Z", "OrderId": "b120595a-f67b-4f05-8ba1-b2c77721f24e"}}
{"Type": "OrderPlaced", "Data": {"TimeStampUtc": "2018-10-03T23:39:02Z", "OrderId": "6d7f7cf9-e3ec-4863-92b8-cbe7fe6478a8"}}
{"Type": "OrderCancelled", "Data": {"TimeStampUtc": "2018-10-03T23:39:02Z", "OrderId": "6d7f7cf9-e3ec-4863-92b8-cbe7fe6478a8"}}
{"Type": "OrderPlaced", "Data": {"TimeStampUtc": "2018-10-03T23:39:02Z", "OrderId": "79714aab-8779-4e69-b7cc-3a66e0e323ee"}}
{"Type": "OrderAccepted", "Data": {"TimeStampUtc": "2018-10-03T23:39:02Z", "OrderId": "79714aab-8779-4e69-b7cc-3a66e0e323ee"}}
{"Type": "OrderPlaced", "Data": {"TimeStampUtc": "2018-10-03T23:39:02Z", "OrderId": "b9316b0f-a6af-4943-9a37-f30aeb04195d"}}
{"Type": "OrderCancelled", "Data": {"TimeStampUtc": "2018-10-03T23:39:02Z", "OrderId": "b9316b0f-a6af-4943-9a37-f30aeb04195d"}}
{"Type": "OrderPlaced", "Data": {"TimeStampUtc": "2018-10-03T23:39:02Z", "OrderId": "40ece6f8-5397-426e-805e-249f043877d4"}}
{"Type": "OrderCancelled", "Data": {"TimeStampUtc": "2018-10-03T23:39:02Z", "OrderId": "40ece6f8-5397-426e-805e-249f043877d4"}}
{"Type": "OrderPlaced", "Data": {"TimeStampUtc": "2018-10-03T23:39:02Z", "OrderId": "202d1c6f-62ce-444b-b215-71623c96b45c"}}
{"Type": "OrderAccepted", "Data": {"TimeStampUtc": "2018-10-03T23:39:02Z", "OrderId": "202d1c6f-62ce-444b-b215-71623c96b45c"}}
